azure_cli_ml-0.1.0a27.post3-py3.5-nspkg.pth
azure/cli/command_modules/ml/__init__.py
azure/cli/command_modules/ml/_acs_util.py
azure/cli/command_modules/ml/_aml_help_formatter.py
azure/cli/command_modules/ml/_az_util.py
azure/cli/command_modules/ml/_compute_util.py
azure/cli/command_modules/ml/_constants.py
azure/cli/command_modules/ml/_endpoints_utill.py
azure/cli/command_modules/ml/_get_logs.py
azure/cli/command_modules/ml/_help.py
azure/cli/command_modules/ml/_host_account_util.py
azure/cli/command_modules/ml/_image_util.py
azure/cli/command_modules/ml/_k8s_util.py
azure/cli/command_modules/ml/_manifest_util.py
azure/cli/command_modules/ml/_ml_cli_error.py
azure/cli/command_modules/ml/_model_management_account_util.py
azure/cli/command_modules/ml/_model_util.py
azure/cli/command_modules/ml/_package_util.py
azure/cli/command_modules/ml/_params.py
azure/cli/command_modules/ml/_transformers.py
azure/cli/command_modules/ml/_util.py
azure/cli/command_modules/ml/_util_BACKUP_30524.py
azure/cli/command_modules/ml/_util_BASE_30524.py
azure/cli/command_modules/ml/_util_LOCAL_30524.py
azure/cli/command_modules/ml/_util_REMOTE_30524.py
azure/cli/command_modules/ml/_validators.py
azure/cli/command_modules/ml/all_parameters.py
azure/cli/command_modules/ml/command_details.json
azure/cli/command_modules/ml/commands.py
azure/cli/command_modules/ml/commands_utility.py
azure/cli/command_modules/ml/compute.py
azure/cli/command_modules/ml/endpoints.py
azure/cli/command_modules/ml/env.py
azure/cli/command_modules/ml/host_account.py
azure/cli/command_modules/ml/image.py
azure/cli/command_modules/ml/manifest.py
azure/cli/command_modules/ml/model.py
azure/cli/command_modules/ml/model_management_account.py
azure/cli/command_modules/ml/package.py
azure/cli/command_modules/ml/_mlc/__init__.py
azure/cli/command_modules/ml/_mlc/machine_learning_compute_management_client.py
azure/cli/command_modules/ml/_mlc/version.py
azure_cli_ml-0.1.0a27.post3.dist-info/DESCRIPTION.rst
azure_cli_ml-0.1.0a27.post3.dist-info/METADATA
azure_cli_ml-0.1.0a27.post3.dist-info/RECORD
azure_cli_ml-0.1.0a27.post3.dist-info/WHEEL
azure_cli_ml-0.1.0a27.post3.dist-info/metadata.json
azure_cli_ml-0.1.0a27.post3.dist-info/namespace_packages.txt
azure_cli_ml-0.1.0a27.post3.dist-info/top_level.txt
