Metadata-Version: 2.0
Name: azure-cli-ml
Version: 0.1.0a27.post3
Summary: Microsoft Azure Command-Line Tools AzureML Command Module
Home-page: https://github.com/Azure/azure-cli
Author: Microsoft Corporation
Author-email: azpycli@microsoft.com
License: MIT
Platform: UNKNOWN
Classifier: Development Status :: 3 - Alpha
Classifier: Intended Audience :: Developers
Classifier: Intended Audience :: System Administrators
Classifier: License :: OSI Approved :: MIT License
Classifier: Programming Language :: Python :: 2.7
Classifier: Programming Language :: Python :: 3.5
Requires-Dist: adal (>=0.4.7)
Requires-Dist: azure-cli-core
Requires-Dist: azure-graphrbac (>=0.31.0)
Requires-Dist: azure-mgmt-compute (>=2.1.0)
Requires-Dist: azure-mgmt-containerregistry (>=0.3.1)
Requires-Dist: azure-mgmt-resource (>=1.1.0)
Requires-Dist: azure-mgmt-storage (>=1.3.0)
Requires-Dist: azure-ml-api-sdk (==0.1.0a11)
Requires-Dist: azure-storage (>=0.36.0)
Requires-Dist: docker (>=2.5.1)
Requires-Dist: future (>=0.16.0)
Requires-Dist: kubernetes (>=3.0.0)
Requires-Dist: msrest (>=0.4.16)
Requires-Dist: pyyaml (>=3.12.0)
Requires-Dist: requests (>=2.18.1)
Requires-Dist: scp (>=0.10.2)
Requires-Dist: tabulate (>=0.7.7)
